gdbuild/__init__.py
gdbuild/file_helper.py
gdbuild/gdbuild.py
gdbuild-0.0.1.dist-info/LICENSE
gdbuild-0.0.1.dist-info/METADATA
gdbuild-0.0.1.dist-info/WHEEL
gdbuild-0.0.1.dist-info/top_level.txt
gdbuild-0.0.1.dist-info/RECORD
