Metadata-Version: 2.1
Name: gdbuild
Version: 0.0.1
Summary: A python module used to help building Godot 3.1 games.
Home-page: https://github.com/Chukobyte/GDBuild
Author: Chukobyte
Author-email: chukobyte@gmail.com
License: UNKNOWN
Project-URL: Bug Reports, https://github.com/Chukobyte/GDBuild/issues
Project-URL: Source, https://github.com/Chukobyte/GDBuild
Platform: UNKNOWN
Requires-Python: >=3.5
